{
    "oneliner": {
        "download_brochure": {
            "category": "download_brochure",
            "content": "Join us for an unparalleled networking experience – register now to connect with industry professionals and leaders!",
            "headding": "Download Brochure"
        },
        "important_dates": {
            "category": "important_dates",
            "content": "Stay ahead by marking your calendars with these crucial deadlines for the upcoming VVIC-2026. Timely registration and submissions will ensure you make the most of this premier event.",
            "headding": "Important dates"
        },
        "Explore_Our_Comprehensive_Networking_Services": {
            "category": "Explore_Our_Comprehensive_Networking_Services",
            "content": "Unlock new opportunities and build valuable connections with our comprehensive networking services, tailored to enhance your conference experience.",
            "headding": "Explore Our comprehensive Networking Services"
        },
        "Be_A_Volunteer": {
            "category": "Be_A_Volunteer",
            "content": "Become a volunteer at the <b>Infectious Diseases Conference 2026</b> and help make history in shaping a future health agenda. Bring professional experience and network with the experts for innovative solutions to fight against infectious diseases.",
            "headding": "Be A Volunteer"
        },
        "Submit_Your_Abstract": {
            "category": "Submit_Your_Abstract",
            "content": "Submit your abstract for VVIC 2026 and showcase your innovations in infection prevention and treatment. Contribute to advancing global health today.",
            "headding": "Submit Your Abstract"
        },
        "sessions": {
            "category": "sessions",
            "content": "In this session, leading advances, novel strategies, and collective efforts taken in response to infectious threats will be covered. Infectious Diseases Conference: It will provide a common platform for dealing collectively with worldwide issues associated with infectious diseases.",
            "headding": "Sessions"
        },
        "footer_content": {
            "category": "footer_content",
            "content": "Infectious Diseases Conference 2026 welcomes all you dedicated professionals coming together to explore and learn the latest advancements and best practices in healthcare.",
            "headding": "Footer content"
        },
        "offers_content": {
            "1": {
                "category": "offers_content",
                "content": "<div class=\"col-md-12 wow fadeInUp animated\" data-wow-delay=\"200ms\" data-wow-duration=\"1000ms\" style=\"visibility: visible; animation-duration: 1000ms; animation-delay: 200ms; animation-name: fadeInUp;\">\r\n          <h2>Book by Sep. 2024 &amp; Save $1651!</h2>\r\n          <h3>BRING A COLLEAGUE SAVE $200 TOTAL, BRING MORE, SAVE MORE</h3>\r\n          <a href=\"/register\">Register now</a>\r\n        </div>",
                "headding": "Offers Content"
            },
            "2": {
                "category": "offers_content",
                "content": "<div class=\"col-md-12 wow fadeInUp animated\" data-wow-delay=\"200ms\" data-wow-duration=\"1000ms\" style=\"visibility: visible; animation-duration: 1000ms; animation-delay: 200ms; animation-name: fadeInUp;\">\r\n          <h2>Collaborate with colleagues and enjoy cost savings</h2>\r\n          <h3>Seize the opportunity to attend as a group and save</h3>\r\n          <a href=\"/register\">Register now</a>\r\n        </div>",
                "headding": "Offers Content"
            },
            "3": {
                "category": "offers_content",
                "content": "<div class=\"col-md-12 wow fadeInUp animated\" data-wow-delay=\"200ms\" data-wow-duration=\"1000ms\" style=\"visibility: visible; animation-duration: 1000ms; animation-delay: 200ms; animation-name: fadeInUp;\">\r\n <h2>The More, the Merrier! Register as a group of 3 or more</h2>\r\n <h3>and unlock a 20% discount for everyone!</h3>\r\n <a href=\"/register\">Register now</a>\r\n </div>",
                "headding": "Offers Content"
            },
            "4": {
                "category": "offers_content",
                "content": "<div class=\"col-md-12 wow fadeInUp animated\" data-wow-delay=\"200ms\" data-wow-duration=\"1000ms\" style=\"visibility: visible; animation-duration: 1000ms; animation-delay: 200ms; animation-name: fadeInUp;\">\r\n          <h2>Book by Nov 2024 &amp; Save huge!</h2>\r\n          <h3>BRING A COLLEAGUE SAVE $200 TOTAL, BRING MORE, SAVE MORE</h3>\r\n          <a href=\"/register\" title=\"Register\">Register now</a>\r\n        </div>",
                "headding": "Offers content"
            },
            "5": {
                "category": "offers_content",
                "content": "<div class=\"col-md-12 wow fadeInUp animated\" data-wow-delay=\"200ms\" data-wow-duration=\"1000ms\" style=\"visibility: visible; animation-duration: 1000ms; animation-delay: 200ms; animation-name: fadeInUp;\">\r\n          <h2>Book by Nov 2024 &amp; Save huge!</h2>\r\n          <h3>BRING A COLLEAGUE SAVE $200 TOTAL, BRING MORE, SAVE MORE</h3>\r\n          <a href=\"/register\" title=\"Register\">Register now</a>\r\n        </div>",
                "headding": "Offers content"
            },
            "6": {
                "category": "offers_content",
                "content": "<div class=\"col-md-12 wow fadeInUp animated\" data-wow-delay=\"200ms\" data-wow-duration=\"1000ms\" style=\"visibility: visible; animation-duration: 1000ms; animation-delay: 200ms; animation-name: fadeInUp;\">\r\n          <h2>Book by Nov 2024 &amp; Save huge!</h2>\r\n          <h3>BRING A COLLEAGUE SAVE $200 TOTAL, BRING MORE, SAVE MORE</h3>\r\n          <a href=\"/register\" title=\"Register\">Register now</a>\r\n        </div>",
                "headding": "Offers content"
            }
        }
    },
    "banner_conent": {
        "4": {
            "banner_conent_id": "4",
            "image": "images/banner.jpg",
            "headding": "Global Strategies for Infectious Diseases Control: Challenges and Innovations",
            "tag_line": "Infectious Diseases-VVIC September 22-23, 2026 in Berlin, Germany",
            "content": "Download your VVIC-2026 brochure now to learn more about a complete program agenda, influential speakers, and foresight into discussions on global health. Stay updated and join this lively, interactive event. Download now!",
            "page": "index",
            "status": "1",
            "cid": "10038"
        }
    },
    "sessions": [
        {
            "text": "1. Pandemic Preparedness and Response",
            "link": "pandemic-preparedness-and-response",
            "session_short_name": "Pandemic Preparedness and Response"
        },
        {
            "text": "2.\tEmerging Infectious Diseases",
            "link": "antimicrobial-resistance-(amr)",
            "session_short_name": "Emerging Infectious Diseases"
        },
        {
            "text": "3. Bacterial Infectious Diseases",
            "link": "bacterial-infectious-diseases",
            "session_short_name": "Bacterial Infectious Diseases"
        },
        {
            "text": "4.\tOne Health Approach",
            "link": "one-health-approach",
            "session_short_name": "One Health Approach"
        },
        {
            "text": "5.\tGlobal Health Security",
            "link": "global-health-security",
            "session_short_name": "Global Health Security"
        },
        {
            "text": "6.\tTropical Infectious Diseases",
            "link": "tropical-infectious-diseases",
            "session_short_name": "Tropical Infectious Diseases"
        },
        {
            "text": "7. Sexually Transmitted Diseases",
            "link": "sexually-transmitted-diseases",
            "session_short_name": "Sexually Transmitted Diseases"
        },
        {
            "text": "8. Emerging Infectious Diseases",
            "link": "emerging-infectious-diseases",
            "session_short_name": "Emerging Infectious Diseases"
        },
        {
            "text": "9.\tMicro biome Role in Diseases",
            "link": "micro-biome-role-in-diseases",
            "session_short_name": "Micro biome Role in Diseases"
        },
        {
            "text": "10.\tEmerging and Re-emerging Infectious Diseases",
            "link": "emerging-and-re-emerging-infectious-diseases",
            "session_short_name": "Emerging and Re-emerging Infectious Diseases"
        }
    ],
    "important_dates": [
        {
            "text": "First Round of Abstract Submission Deadline",
            "date": "28<sub>th</sub> <span>November <br> 2025</span>"
        },
        {
            "text": "Early Bird Registration Deadline",
            "date": "28<sub>th</sub> <span>November <br> 2025</span>"
        }
    ],
    "venue_images": {
        "41": {
            "image": "images/g1.webp",
            "alt_text": "Berlin Cathedral"
        },
        "42": {
            "image": "images/g2.webp",
            "alt_text": "Potsdamer Platz"
        },
        "43": {
            "image": "images/g3.webp",
            "alt_text": "Brandenburg Gate"
        },
        "44": {
            "image": "images/g4.webp",
            "alt_text": "Charlottenburg Palace"
        }
    }
}